coniql/__init__.py
coniql/__main__.py
coniql/_version.py
coniql/app.py
coniql/caplugin.py
coniql/coniql_schema.py
coniql/metrics.py
coniql/plugin.py
coniql/simplugin.py
coniql/strawberry_schema.py
coniql/types.py
coniql-0.4.2.dist-info/LICENSE
coniql-0.4.2.dist-info/METADATA
coniql-0.4.2.dist-info/WHEEL
coniql-0.4.2.dist-info/entry_points.txt
coniql-0.4.2.dist-info/top_level.txt
coniql-0.4.2.dist-info/RECORD
