Metadata-Version: 2.1
Name: coniql
Version: 0.4.2
Summary: Interface to control systems via GraphQL over websockets
Author-email: Tom Cobb <tom.cobbl@diamond.ac.uk>
License: Apache License
Project-URL: GitHub, https://github.com/DiamondLightSource/coniql
Classifier: Development Status :: 4 - Beta
Classifier: License :: OSI Approved :: Apache Software License
Classifier: Programming Language :: Python :: 3.8
Classifier: Programming Language :: Python :: 3.9
Classifier: Programming Language :: Python :: 3.10
Classifier: Programming Language :: Python :: 3.11
Requires-Python: >=3.8
License-File: LICENSE
Requires-Dist: strawberry-graphql ==0.190.0
Requires-Dist: aioca >=1.7
Requires-Dist: p4p
Requires-Dist: ruamel.yaml
Requires-Dist: aiohttp-cors
Requires-Dist: aioprometheus
Requires-Dist: setuptools >=67
Requires-Dist: typing-extensions ; python_version < "3.8"
Provides-Extra: dev
Requires-Dist: black ; extra == 'dev'
Requires-Dist: mypy ; extra == 'dev'
Requires-Dist: flake8-isort ; extra == 'dev'
Requires-Dist: Flake8-pyproject ; extra == 'dev'
Requires-Dist: pipdeptree ; extra == 'dev'
Requires-Dist: pre-commit ; extra == 'dev'
Requires-Dist: pytest ; extra == 'dev'
Requires-Dist: pytest-cov ; extra == 'dev'
Requires-Dist: sphinx-autobuild ; extra == 'dev'
Requires-Dist: sphinx-copybutton ; extra == 'dev'
Requires-Dist: sphinx-design ; extra == 'dev'
Requires-Dist: sphinx-rtd-theme-github-versions ; extra == 'dev'
Requires-Dist: tox-direct ; extra == 'dev'
Requires-Dist: types-mock ; extra == 'dev'
Requires-Dist: psutil ; extra == 'dev'
Requires-Dist: pytest-asyncio >0.17 ; extra == 'dev'
Requires-Dist: pytest-aiohttp ; extra == 'dev'
Requires-Dist: types-ujson ; extra == 'dev'
Requires-Dist: ujson ; extra == 'dev'
Requires-Dist: websockets ; extra == 'dev'
